colorsnap/__init__.py
colorsnap/color_snap.py
colorsnap/palettes/__init__.py
colorsnap/palettes/css_2.py
colorsnap/palettes/css_2_1.py
colorsnap/palettes/css_3.py
colorsnap/palettes/css_4.py
colorsnap-1.0.1.dist-info/METADATA
colorsnap-1.0.1.dist-info/RECORD
colorsnap-1.0.1.dist-info/WHEEL
colorsnap-1.0.1.dist-info/top_level.txt
