Metadata-Version: 2.1
Name: colorsnap
Version: 1.0.1
Summary: Python package for snaping/rounding colors to other colors/palettes.
Home-page: https://github.com/riksantikvareambetet/colorsnap
Author: Albin Larsson
Author-email: albin.larsson@raa.se
License: MIT
Download-URL: https://github.com/riksantikvareambetet/colorsnap/tarball/1.0.1
Keywords: heritage,cultural
Platform: UNKNOWN
Classifier: License :: OSI Approved :: MIT License
Classifier: Programming Language :: Python
Classifier: Programming Language :: Python :: 3
Classifier: Programming Language :: Python :: 3.6
Classifier: Programming Language :: Python :: 3.7
Classifier: Programming Language :: Python :: 3 :: Only
Classifier: Intended Audience :: Developers
Classifier: Intended Audience :: Education
Requires-Python: >=3.6.0
